gatenlp_ml_tner/__init__.py
gatenlp_ml_tner/annotators.py
gatenlp_ml_tner/eval.py
gatenlp_ml_tner/export.py
gatenlp_ml_tner/train.py
gatenlp_ml_tner/version.py
gatenlp_ml_tner-0.1.0a1.dist-info/LICENSE
gatenlp_ml_tner-0.1.0a1.dist-info/METADATA
gatenlp_ml_tner-0.1.0a1.dist-info/WHEEL
gatenlp_ml_tner-0.1.0a1.dist-info/entry_points.txt
gatenlp_ml_tner-0.1.0a1.dist-info/top_level.txt
gatenlp_ml_tner-0.1.0a1.dist-info/RECORD
